vcbblueprint.py
vcbblueprint-0.1.1.dist-info/METADATA
vcbblueprint-0.1.1.dist-info/WHEEL
vcbblueprint-0.1.1.dist-info/licenses/LICENSE
vcbblueprint-0.1.1.dist-info/RECORD
