Metadata-Version: 2.1
Name: vcbblueprint
Version: 0.1.1
Summary: A library for decoding Virtual Circuit Board blueprint strings
Project-URL: Homepage, https://github.com/bmander/vcbblueprint/
Project-URL: Repository, https://github.com/bmander/vcbblueprint.git
Author-email: Brandon Martin-Anderson <badhill@gmail.com>
License: MIT License
License-File: LICENSE
Keywords: blueprint,vcb,virtual circuit board
Classifier: License :: OSI Approved :: MIT License
Classifier: Operating System :: OS Independent
Classifier: Programming Language :: Python :: 3
Requires-Python: >=3.9
Requires-Dist: numpy~=1.24.0
Requires-Dist: zstd~=1.5.0
